voicerss_tts/__init__.py
voicerss_tts/_metadata.py
voicerss_tts/example.py
voicerss_tts/voicerss_tts.py
voicerss_tts-1.0.6.dist-info/LICENSE.txt
voicerss_tts-1.0.6.dist-info/METADATA
voicerss_tts-1.0.6.dist-info/WHEEL
voicerss_tts-1.0.6.dist-info/entry_points.txt
voicerss_tts-1.0.6.dist-info/top_level.txt
voicerss_tts-1.0.6.dist-info/RECORD
