Metadata-Version: 2.1
Name: voicerss-tts
Version: 1.0.6
Summary: A collection of table creation utilities.
Home-page: https://bitbucket.org/daycoder/voicerss_tts.git
Author: Hywel Thomas
Author-email: hywel.thomas@mac.com
License: MIT
Download-URL: https://bitbucket.org/daycoder/voicerss_tts.git/get/1.0.6.tar
Platform: UNKNOWN
Classifier: Development Status :: 3 - Alpha
Classifier: Intended Audience :: Developers
Classifier: License :: OSI Approved :: MIT License
Classifier: Programming Language :: Python :: 2
Classifier: Programming Language :: Python :: 2.7
Classifier: Programming Language :: Python :: 3
Classifier: Programming Language :: Python :: 3.6
Classifier: Topic :: Utilities
Requires-Dist: pip (>=18.1)
Requires-Dist: future (>=0.16.0)
Requires-Dist: logging-helper (>=1.7.0)
Requires-Dist: fdutil (>=1.6.4)
Requires-Dist: cachingutil (>=1.0.18)
Requires-Dist: requests (>=2.19.1)
Provides-Extra: test
